takeusecases/__init__.py
takeusecases/util.py
takeusecases/ml/__init__.py
takeusecases/ml/data_source/__init__.py
takeusecases/ml/data_source/base.py
takeusecases/ml/data_source/database.py
takeusecases/ml/model/__init__.py
takeusecases/ml/model/metrics.py
takeusecases/ml/model/trainer.py
takeusecases/ml/model/wrapper.py
takeusecases/ml/preprocessing/__init__.py
takeusecases/ml/preprocessing/preprocessing.py
takeusecases/ml/preprocessing/preprocessing_messages.py
takeusecases/ml/preprocessing/text_vectorizer.py
takeusecases-0.0.13.dist-info/METADATA
takeusecases-0.0.13.dist-info/WHEEL
takeusecases-0.0.13.dist-info/top_level.txt
takeusecases-0.0.13.dist-info/RECORD
