Metadata-Version: 2.1
Name: takeusecases
Version: 0.0.13
Summary: A clustering based approach to inferring the use case of an intelligent contact. Developed by A3Data, packaged by D&A Research - Take Blip.
Home-page: UNKNOWN
Author: A3Data / Data & Analytics Research
Author-email: <analytics.dar@take.net>
Maintainer: daresearch
License: MIT License
Keywords: take blip,intelligent contact,use cases,clustering
Platform: UNKNOWN
Classifier: Development Status :: 1 - Planning
Classifier: Intended Audience :: Developers
Classifier: Programming Language :: Python :: 3
Classifier: Operating System :: Unix
Classifier: Operating System :: MacOS :: MacOS X
Classifier: Operating System :: Microsoft :: Windows
Requires-Dist: datetime
Requires-Dist: gensim (==3.8.3)
Requires-Dist: joblib
Requires-Dist: mlflow
Requires-Dist: numpy (==1.19.2)
Requires-Dist: pandas
Requires-Dist: pathlib2
Requires-Dist: requests
Requires-Dist: scipy
Requires-Dist: seaborn
Requires-Dist: spacy
Requires-Dist: statsmodels
Requires-Dist: tqdm
Requires-Dist: TakeSentenceTokenizer (==1.0.1)
Requires-Dist: scikit-learn (==0.24.1)
